odoo/addons/pos_accented_search/README.rst
odoo/addons/pos_accented_search/__init__.py
odoo/addons/pos_accented_search/__manifest__.py
odoo/addons/pos_accented_search/i18n/pos_accented_search.pot
odoo/addons/pos_accented_search/readme/CONTRIBUTORS.rst
odoo/addons/pos_accented_search/readme/DESCRIPTION.rst
odoo/addons/pos_accented_search/readme/USAGE.rst
odoo/addons/pos_accented_search/static/description/icon.png
odoo/addons/pos_accented_search/static/description/index.html
odoo/addons/pos_accented_search/static/src/js/db.js
odoo/addons/pos_accented_search/views/templates.xml
odoo12_addon_pos_accented_search-12.0.1.0.1.dist-info/METADATA
odoo12_addon_pos_accented_search-12.0.1.0.1.dist-info/WHEEL
odoo12_addon_pos_accented_search-12.0.1.0.1.dist-info/top_level.txt
odoo12_addon_pos_accented_search-12.0.1.0.1.dist-info/RECORD
