Metadata-Version: 2.1
Name: odoo12-addon-pos-accented-search
Version: 12.0.1.0.1
Summary: Point of Sale - Product search works regardless of accented characters
Home-page: https://github.com/OCA/pos
Author: Le Nid, Odoo Community Association (OCA)
Author-email: support@odoo-community.org
License: AGPL-3
Platform: UNKNOWN
Classifier: Programming Language :: Python
Classifier: Framework :: Odoo
Classifier: License :: OSI Approved :: GNU Affero General Public License v3
Requires-Python: >=3.5
Requires-Dist: odoo (<12.1dev,>=12.0a)
